[
  {
    "completion_time": 70719,
    "platform": "WIN",
    "platform_name": "一Tex一",
    "rank": 1,
    "weapon": 4
  },
  {
    "completion_time": 71657,
    "platform": "WIN",
    "platform_name": "Çosplay",
    "rank": 2,
    "weapon": 7
  },
  {
    "completion_time": 73799,
    "platform": "WIN",
    "platform_name": "genrofuG",
    "rank": 3,
    "weapon": 4
  },
  {
    "completion_time": 74012,
    "platform": "WIN",
    "platform_name": "Hawks_PJDK15",
    "rank": 4,
    "weapon": 4
  },
  {
    "completion_time": 74576,
    "platform": "WIN",
    "platform_name": "TurkuazBülbül",
    "rank": 5,
    "weapon": 4
  },
  {
    "completion_time": 75576,
    "platform": "PSN",
    "platform_name": "Killing_Laugh",
    "rank": 6,
    "weapon": 4
  },
  {
    "completion_time": 75684,
    "platform": "WIN",
    "platform_name": "Techker7 ツ",
    "rank": 7,
    "weapon": 4
  },
  {
    "completion_time": 75912,
    "platform": "WIN",
    "platform_name": "G.F.Joe13",
    "rank": 8,
    "weapon": 4
  },
  {
    "completion_time": 77504,
    "platform": "WIN",
    "platform_name": "johanril",
    "rank": 9,
    "weapon": 4
  },
  {
    "completion_time": 77607,
    "platform": "WIN",
    "platform_name": "The Veslování 真混",
    "rank": 10,
    "weapon": 7
  },
  {
    "completion_time": 78479,
    "platform": "WIN",
    "platform_name": "Lupula",
    "rank": 11,
    "weapon": 4
  },
  {
    "completion_time": 79154,
    "platform": "PSN",
    "platform_name": "SGA315",
    "rank": 12,
    "weapon": 4
  },
  {
    "completion_time": 79334,
    "platform": "XBL",
    "platform_name": "Nehqzi",
    "rank": 13,
    "weapon": 4
  },
  {
    "completion_time": 79852,
    "platform": "WIN",
    "platform_name": "Void丨Shadow",
    "rank": 14,
    "weapon": 4
  },
  {
    "completion_time": 80059,
    "platform": "WIN",
    "platform_name": "Insanaire",
    "rank": 15,
    "weapon": 4
  },
  {
    "completion_time": 80613,
    "platform": "WIN",
    "platform_name": "not 1lxe",
    "rank": 16,
    "weapon": 4
  },
  {
    "completion_time": 80644,
    "platform": "WIN",
    "platform_name": "Radazuken",
    "rank": 17,
    "weapon": 4
  },
  {
    "completion_time": 80666,
    "platform": "WIN",
    "platform_name": "ZionEstes",
    "rank": 18,
    "weapon": 4
  },
  {
    "completion_time": 80845,
    "platform": "WIN",
    "platform_name": "IV Praetorian",
    "rank": 19,
    "weapon": 4
  },
  {
    "completion_time": 81292,
    "platform": "WIN",
    "platform_name": "cow_bell88",
    "rank": 20,
    "weapon": 4
  },
  {
    "completion_time": 81851,
    "platform": "PSN",
    "platform_name": "DottHaze",
    "rank": 21,
    "weapon": 4
  },
  {
    "completion_time": 82295,
    "platform": "XBL",
    "platform_name": "VI Ringss",
    "rank": 22,
    "weapon": 4
  },
  {
    "completion_time": 82588,
    "platform": "WIN",
    "platform_name": "難敵你是你來負我是我的道",
    "rank": 23,
    "weapon": 4
  },
  {
    "completion_time": 82842,
    "platform": "PSN",
    "platform_name": "Phenom_707",
    "rank": 24,
    "weapon": 4
  },
  {
    "completion_time": 82901,
    "platform": "WIN",
    "platform_name": "TheChuckSmile",
    "rank": 25,
    "weapon": 4
  },
  {
    "completion_time": 82992,
    "platform": "WIN",
    "platform_name": "xYx Dante",
    "rank": 26,
    "weapon": 4
  },
  {
    "completion_time": 83035,
    "platform": "WIN",
    "platform_name": "Peng0119",
    "rank": 27,
    "weapon": 4
  },
  {
    "completion_time": 83049,
    "platform": "WIN",
    "platform_name": "DeerEdits",
    "rank": 28,
    "weapon": 4
  },
  {
    "completion_time": 83177,
    "platform": "WIN",
    "platform_name": "ramter01210",
    "rank": 29,
    "weapon": 4
  },
  {
    "completion_time": 83359,
    "platform": "WIN",
    "platform_name": "KENZO来",
    "rank": 30,
    "weapon": 4
  },
  {
    "completion_time": 83569,
    "platform": "WIN",
    "platform_name": "TTrinxx",
    "rank": 31,
    "weapon": 4
  },
  {
    "completion_time": 83810,
    "platform": "WIN",
    "platform_name": "SaûdiSlayer",
    "rank": 32,
    "weapon": 4
  },
  {
    "completion_time": 83851,
    "platform": "PSN",
    "platform_name": "YG-F",
    "rank": 33,
    "weapon": 4
  },
  {
    "completion_time": 83865,
    "platform": "WIN",
    "platform_name": "にゃあ_JP",
    "rank": 34,
    "weapon": 4
  },
  {
    "completion_time": 83884,
    "platform": "WIN",
    "platform_name": "LollyGags",
    "rank": 35,
    "weapon": 4
  },
  {
    "completion_time": 83900,
    "platform": "WIN",
    "platform_name": "Sovieta",
    "rank": 36,
    "weapon": 4
  },
  {
    "completion_time": 84107,
    "platform": "XBL",
    "platform_name": "Pacquiau1998",
    "rank": 37,
    "weapon": 4
  },
  {
    "completion_time": 84395,
    "platform": "WIN",
    "platform_name": "Stiorz",
    "rank": 38,
    "weapon": 4
  },
  {
    "completion_time": 84716,
    "platform": "PSN",
    "platform_name": "Abubagasa",
    "rank": 39,
    "weapon": 4
  },
  {
    "completion_time": 84743,
    "platform": "WIN",
    "platform_name": "InstaKosmo-",
    "rank": 40,
    "weapon": 4
  },
  {
    "completion_time": 84911,
    "platform": "WIN",
    "platform_name": "Irish 神様",
    "rank": 41,
    "weapon": 4
  },
  {
    "completion_time": 85015,
    "platform": "WIN",
    "platform_name": "GeorgesLeYeti",
    "rank": 42,
    "weapon": 4
  },
  {
    "completion_time": 85044,
    "platform": "XBL",
    "platform_name": "SoRZeRo",
    "rank": 43,
    "weapon": 4
  },
  {
    "completion_time": 85132,
    "platform": "WIN",
    "platform_name": "拂花影動",
    "rank": 44,
    "weapon": 4
  },
  {
    "completion_time": 85378,
    "platform": "WIN",
    "platform_name": "Kosmos_btw",
    "rank": 45,
    "weapon": 4
  },
  {
    "completion_time": 85596,
    "platform": "PSN",
    "platform_name": "Z4MuR41D",
    "rank": 46,
    "weapon": 4
  },
  {
    "completion_time": 85803,
    "platform": "PSN",
    "platform_name": "curo-guro",
    "rank": 47,
    "weapon": 4
  },
  {
    "completion_time": 86383,
    "platform": "WIN",
    "platform_name": "skeewunna",
    "rank": 48,
    "weapon": 4
  },
  {
    "completion_time": 86466,
    "platform": "WIN",
    "platform_name": "Bärtiger Bär",
    "rank": 49,
    "weapon": 4
  },
  {
    "completion_time": 86619,
    "platform": "WIN",
    "platform_name": "Vina Garutz",
    "rank": 50,
    "weapon": 4
  },
  {
    "completion_time": 86673,
    "platform": "WIN",
    "platform_name": "MoroccanPsycho",
    "rank": 51,
    "weapon": 4
  },
  {
    "completion_time": 87323,
    "platform": "WIN",
    "platform_name": "Thanatos_ji",
    "rank": 52,
    "weapon": 4
  },
  {
    "completion_time": 87551,
    "platform": "WIN",
    "platform_name": "Az 薔薇蘇青衣",
    "rank": 53,
    "weapon": 4
  },
  {
    "completion_time": 87814,
    "platform": "WIN",
    "platform_name": "Kaba4oк",
    "rank": 54,
    "weapon": 4
  },
  {
    "completion_time": 87933,
    "platform": "SWT",
    "platform_name": "black",
    "rank": 55,
    "weapon": 4
  },
  {
    "completion_time": 88099,
    "platform": "WIN",
    "platform_name": "Cheese 935",
    "rank": 56,
    "weapon": 7
  },
  {
    "completion_time": 88256,
    "platform": "WIN",
    "platform_name": "M Ø N K Ξ",
    "rank": 57,
    "weapon": 4
  },
  {
    "completion_time": 88703,
    "platform": "WIN",
    "platform_name": "PYXIS5",
    "rank": 58,
    "weapon": 4
  },
  {
    "completion_time": 88704,
    "platform": "PSN",
    "platform_name": "lord_pollon81",
    "rank": 59,
    "weapon": 4
  },
  {
    "completion_time": 88799,
    "platform": "WIN",
    "platform_name": "顎izm",
    "rank": 60,
    "weapon": 4
  },
  {
    "completion_time": 88801,
    "platform": "WIN",
    "platform_name": "StormunD",
    "rank": 61,
    "weapon": 4
  },
  {
    "completion_time": 88827,
    "platform": "WIN",
    "platform_name": "JohtoChamp",
    "rank": 62,
    "weapon": 4
  },
  {
    "completion_time": 88888,
    "platform": "WIN",
    "platform_name": "Rjet824",
    "rank": 63,
    "weapon": 4
  },
  {
    "completion_time": 88945,
    "platform": "WIN",
    "platform_name": "XΞΘ",
    "rank": 64,
    "weapon": 4
  },
  {
    "completion_time": 88969,
    "platform": "WIN",
    "platform_name": "Bhorg",
    "rank": 65,
    "weapon": 4
  },
  {
    "completion_time": 89181,
    "platform": "WIN",
    "platform_name": "G La Frite ツ",
    "rank": 66,
    "weapon": 4
  },
  {
    "completion_time": 89253,
    "platform": "WIN",
    "platform_name": "BlazeLawliet",
    "rank": 67,
    "weapon": 4
  },
  {
    "completion_time": 89424,
    "platform": "WIN",
    "platform_name": "エンジョイ勢のくっきぃ",
    "rank": 68,
    "weapon": 4
  },
  {
    "completion_time": 89466,
    "platform": "PSN",
    "platform_name": "vSkillum1natv",
    "rank": 69,
    "weapon": 4
  },
  {
    "completion_time": 89534,
    "platform": "WIN",
    "platform_name": "Mr.Sartis",
    "rank": 70,
    "weapon": 4
  },
  {
    "completion_time": 89859,
    "platform": "PSN",
    "platform_name": "Adrianeitor_yolo",
    "rank": 71,
    "weapon": 4
  },
  {
    "completion_time": 89934,
    "platform": "WIN",
    "platform_name": "Toushiiro",
    "rank": 72,
    "weapon": 4
  },
  {
    "completion_time": 90226,
    "platform": "WIN",
    "platform_name": "MẶNU-ШΨ",
    "rank": 73,
    "weapon": 4
  },
  {
    "completion_time": 90291,
    "platform": "PSN",
    "platform_name": "ABOOD1234567-",
    "rank": 74,
    "weapon": 4
  },
  {
    "completion_time": 90363,
    "platform": "PSN",
    "platform_name": "ThorRagnarokkr",
    "rank": 75,
    "weapon": 4
  },
  {
    "completion_time": 90371,
    "platform": "PSN",
    "platform_name": "dashingUX",
    "rank": 76,
    "weapon": 4
  },
  {
    "completion_time": 90395,
    "platform": "PSN",
    "platform_name": "IYomie",
    "rank": 77,
    "weapon": 4
  },
  {
    "completion_time": 90479,
    "platform": "WIN",
    "platform_name": "Toadyy_",
    "rank": 78,
    "weapon": 4
  },
  {
    "completion_time": 90590,
    "platform": "WIN",
    "platform_name": "WØlfeye",
    "rank": 79,
    "weapon": 4
  },
  {
    "completion_time": 90719,
    "platform": "PSN",
    "platform_name": "TranKyTT",
    "rank": 80,
    "weapon": 4
  },
  {
    "completion_time": 90734,
    "platform": "PSN",
    "platform_name": "Mizo3322",
    "rank": 81,
    "weapon": 4
  },
  {
    "completion_time": 90750,
    "platform": "WIN",
    "platform_name": "EnduranceQ",
    "rank": 82,
    "weapon": 4
  },
  {
    "completion_time": 90928,
    "platform": "XBL",
    "platform_name": "JoaKo0",
    "rank": 83,
    "weapon": 4
  },
  {
    "completion_time": 90974,
    "platform": "WIN",
    "platform_name": "Warfarrer77",
    "rank": 84,
    "weapon": 4
  },
  {
    "completion_time": 91166,
    "platform": "PSN",
    "platform_name": "Vioneir",
    "rank": 85,
    "weapon": 4
  },
  {
    "completion_time": 91381,
    "platform": "PSN",
    "platform_name": "unk-nown8",
    "rank": 86,
    "weapon": 4
  },
  {
    "completion_time": 91609,
    "platform": "WIN",
    "platform_name": "IND_Suwandy",
    "rank": 87,
    "weapon": 4
  },
  {
    "completion_time": 91684,
    "platform": "WIN",
    "platform_name": "OishiiKat",
    "rank": 88,
    "weapon": 4
  },
  {
    "completion_time": 91772,
    "platform": "PSN",
    "platform_name": "COFFEE--TEA",
    "rank": 89,
    "weapon": 4
  },
  {
    "completion_time": 91814,
    "platform": "WIN",
    "platform_name": "The 空条Jo太郎",
    "rank": 90,
    "weapon": 4
  },
  {
    "completion_time": 91861,
    "platform": "PSN",
    "platform_name": "Anatar1989",
    "rank": 91,
    "weapon": 4
  },
  {
    "completion_time": 91957,
    "platform": "XBL",
    "platform_name": "BionicBoom88",
    "rank": 92,
    "weapon": 4
  },
  {
    "completion_time": 92217,
    "platform": "WIN",
    "platform_name": "Kuschdii",
    "rank": 93,
    "weapon": 4
  },
  {
    "completion_time": 92329,
    "platform": "WIN",
    "platform_name": "Babynick24",
    "rank": 94,
    "weapon": 4
  },
  {
    "completion_time": 92495,
    "platform": "PSN",
    "platform_name": "KizmaAzul",
    "rank": 95,
    "weapon": 4
  },
  {
    "completion_time": 93060,
    "platform": "WIN",
    "platform_name": "TheUnthinkabl3tv",
    "rank": 96,
    "weapon": 4
  },
  {
    "completion_time": 93096,
    "platform": "PSN",
    "platform_name": "DeViL_LoRisPek",
    "rank": 97,
    "weapon": 4
  },
  {
    "completion_time": 93288,
    "platform": "SWT",
    "platform_name": "ハヤーシーG",
    "rank": 98,
    "weapon": 4
  },
  {
    "completion_time": 93312,
    "platform": "WIN",
    "platform_name": "你好奥利給啊",
    "rank": 99,
    "weapon": 7
  },
  {
    "completion_time": 93323,
    "platform": "PSN",
    "platform_name": "Sluggy_J",
    "rank": 100,
    "weapon": 4
  }
]
