[
  {
    "completion_time": 36756,
    "platform": "WIN",
    "platform_name": "SoloBurst",
    "rank": 1,
    "weapon": 7
  },
  {
    "completion_time": 36779,
    "platform": "WIN",
    "platform_name": "Axermain",
    "rank": 2,
    "weapon": 7
  },
  {
    "completion_time": 36882,
    "platform": "WIN",
    "platform_name": "Mist Noche",
    "rank": 3,
    "weapon": 7
  },
  {
    "completion_time": 36898,
    "platform": "PSN",
    "platform_name": "Batzynator",
    "rank": 4,
    "weapon": 7
  },
  {
    "completion_time": 36922,
    "platform": "WIN",
    "platform_name": "AverageT TTV",
    "rank": 5,
    "weapon": 7
  },
  {
    "completion_time": 36939,
    "platform": "WIN",
    "platform_name": "Derperifica",
    "rank": 6,
    "weapon": 7
  },
  {
    "completion_time": 37259,
    "platform": "WIN",
    "platform_name": "Heltrix-",
    "rank": 7,
    "weapon": 7
  },
  {
    "completion_time": 37349,
    "platform": "WIN",
    "platform_name": "Jeshmh",
    "rank": 8,
    "weapon": 7
  },
  {
    "completion_time": 37525,
    "platform": "WIN",
    "platform_name": "Thirty-",
    "rank": 9,
    "weapon": 7
  },
  {
    "completion_time": 38341,
    "platform": "PSN",
    "platform_name": "xReSiNg__AeRoZx",
    "rank": 10,
    "weapon": 7
  },
  {
    "completion_time": 38395,
    "platform": "WIN",
    "platform_name": "Shaanks",
    "rank": 11,
    "weapon": 7
  },
  {
    "completion_time": 38568,
    "platform": "WIN",
    "platform_name": "FaffyPancakes",
    "rank": 12,
    "weapon": 7
  },
  {
    "completion_time": 38677,
    "platform": "WIN",
    "platform_name": "MrProbeNWatch",
    "rank": 13,
    "weapon": 7
  },
  {
    "completion_time": 39176,
    "platform": "PSN",
    "platform_name": "Expenciv",
    "rank": 14,
    "weapon": 7
  },
  {
    "completion_time": 39390,
    "platform": "WIN",
    "platform_name": "Mc.gros",
    "rank": 15,
    "weapon": 7
  },
  {
    "completion_time": 40246,
    "platform": "WIN",
    "platform_name": "K i L L a N O a",
    "rank": 16,
    "weapon": 7
  },
  {
    "completion_time": 40307,
    "platform": "WIN",
    "platform_name": "Aromatischer_Tee",
    "rank": 17,
    "weapon": 7
  },
  {
    "completion_time": 40785,
    "platform": "WIN",
    "platform_name": "GummBummPlumm",
    "rank": 18,
    "weapon": 7
  },
  {
    "completion_time": 41450,
    "platform": "PSN",
    "platform_name": "xXZanubisXx",
    "rank": 19,
    "weapon": 7
  },
  {
    "completion_time": 42010,
    "platform": "WIN",
    "platform_name": "Nybergz",
    "rank": 20,
    "weapon": 7
  },
  {
    "completion_time": 42586,
    "platform": "WIN",
    "platform_name": "Νapper",
    "rank": 21,
    "weapon": 7
  },
  {
    "completion_time": 43404,
    "platform": "PSN",
    "platform_name": "TorrezLim97",
    "rank": 22,
    "weapon": 7
  },
  {
    "completion_time": 43544,
    "platform": "PSN",
    "platform_name": "DaanH_BR",
    "rank": 23,
    "weapon": 7
  },
  {
    "completion_time": 43986,
    "platform": "WIN",
    "platform_name": "Yap Fr",
    "rank": 24,
    "weapon": 7
  },
  {
    "completion_time": 44482,
    "platform": "PSN",
    "platform_name": "SEQKRIT",
    "rank": 25,
    "weapon": 7
  },
  {
    "completion_time": 44762,
    "platform": "PSN",
    "platform_name": "TUBBZ_13",
    "rank": 26,
    "weapon": 7
  },
  {
    "completion_time": 45048,
    "platform": "WIN",
    "platform_name": "ΘffZera",
    "rank": 27,
    "weapon": 7
  },
  {
    "completion_time": 45321,
    "platform": "WIN",
    "platform_name": "Sabnap",
    "rank": 28,
    "weapon": 7
  },
  {
    "completion_time": 45630,
    "platform": "PSN",
    "platform_name": "Awkward_Geese",
    "rank": 29,
    "weapon": 7
  },
  {
    "completion_time": 46496,
    "platform": "WIN",
    "platform_name": "J.a.t.d.c",
    "rank": 30,
    "weapon": 7
  },
  {
    "completion_time": 46500,
    "platform": "WIN",
    "platform_name": "MrZeroenergy",
    "rank": 31,
    "weapon": 7
  },
  {
    "completion_time": 46751,
    "platform": "PSN",
    "platform_name": "Krazy_707-",
    "rank": 32,
    "weapon": 7
  },
  {
    "completion_time": 47375,
    "platform": "XBL",
    "platform_name": "BoZzofMLG",
    "rank": 33,
    "weapon": 7
  },
  {
    "completion_time": 48116,
    "platform": "WIN",
    "platform_name": "K55VT",
    "rank": 34,
    "weapon": 7
  },
  {
    "completion_time": 48194,
    "platform": "PSN",
    "platform_name": "kui_kun",
    "rank": 35,
    "weapon": 7
  },
  {
    "completion_time": 48622,
    "platform": "WIN",
    "platform_name": "SmogoGod",
    "rank": 36,
    "weapon": 7
  },
  {
    "completion_time": 49643,
    "platform": "WIN",
    "platform_name": "Nlctus",
    "rank": 37,
    "weapon": 7
  },
  {
    "completion_time": 49817,
    "platform": "PSN",
    "platform_name": "E_R_S_OT_888",
    "rank": 38,
    "weapon": 7
  },
  {
    "completion_time": 49919,
    "platform": "WIN",
    "platform_name": "Aceaas",
    "rank": 39,
    "weapon": 7
  },
  {
    "completion_time": 50819,
    "platform": "WIN",
    "platform_name": "BreppSkrepp",
    "rank": 40,
    "weapon": 7
  },
  {
    "completion_time": 51820,
    "platform": "WIN",
    "platform_name": "Annaka_25",
    "rank": 41,
    "weapon": 7
  },
  {
    "completion_time": 52215,
    "platform": "WIN",
    "platform_name": "вeda",
    "rank": 42,
    "weapon": 7
  },
  {
    "completion_time": 52352,
    "platform": "WIN",
    "platform_name": "Cybermessiah",
    "rank": 43,
    "weapon": 7
  },
  {
    "completion_time": 52770,
    "platform": "WIN",
    "platform_name": "KenseVT",
    "rank": 44,
    "weapon": 7
  },
  {
    "completion_time": 53199,
    "platform": "PSN",
    "platform_name": "JPN_96sawaYT",
    "rank": 45,
    "weapon": 7
  },
  {
    "completion_time": 54007,
    "platform": "WIN",
    "platform_name": "mvrod5",
    "rank": 46,
    "weapon": 7
  },
  {
    "completion_time": 54692,
    "platform": "WIN",
    "platform_name": "Jovem Deus 愛",
    "rank": 47,
    "weapon": 7
  },
  {
    "completion_time": 56569,
    "platform": "XBL",
    "platform_name": "Jireu",
    "rank": 48,
    "weapon": 7
  },
  {
    "completion_time": 56625,
    "platform": "PSN",
    "platform_name": "Sk-lash",
    "rank": 49,
    "weapon": 7
  },
  {
    "completion_time": 57298,
    "platform": "WIN",
    "platform_name": "jrseint",
    "rank": 50,
    "weapon": 7
  },
  {
    "completion_time": 57564,
    "platform": "WIN",
    "platform_name": "SUSHlNlNJA",
    "rank": 51,
    "weapon": 7
  },
  {
    "completion_time": 58214,
    "platform": "PSN",
    "platform_name": "goripon1207",
    "rank": 52,
    "weapon": 7
  },
  {
    "completion_time": 59261,
    "platform": "SWT",
    "platform_name": "あょ",
    "rank": 53,
    "weapon": 7
  },
  {
    "completion_time": 59468,
    "platform": "WIN",
    "platform_name": "Sebl4ck",
    "rank": 54,
    "weapon": 7
  },
  {
    "completion_time": 59596,
    "platform": "PSN",
    "platform_name": "XanoOoII",
    "rank": 55,
    "weapon": 7
  },
  {
    "completion_time": 60079,
    "platform": "WIN",
    "platform_name": "Mazıkeen",
    "rank": 56,
    "weapon": 7
  },
  {
    "completion_time": 60285,
    "platform": "PSN",
    "platform_name": "Konz_Young",
    "rank": 57,
    "weapon": 7
  },
  {
    "completion_time": 60298,
    "platform": "WIN",
    "platform_name": "ThiccAddicc",
    "rank": 58,
    "weapon": 7
  },
  {
    "completion_time": 60856,
    "platform": "WIN",
    "platform_name": "ScoobismV2",
    "rank": 59,
    "weapon": 7
  },
  {
    "completion_time": 61059,
    "platform": "WIN",
    "platform_name": "Ｈｉｘｘｙ",
    "rank": 60,
    "weapon": 7
  },
  {
    "completion_time": 61855,
    "platform": "WIN",
    "platform_name": "Raubiiii",
    "rank": 61,
    "weapon": 7
  },
  {
    "completion_time": 61881,
    "platform": "WIN",
    "platform_name": "SOUL774",
    "rank": 62,
    "weapon": 7
  },
  {
    "completion_time": 62377,
    "platform": "PSN",
    "platform_name": "DrJohanfitpro",
    "rank": 63,
    "weapon": 7
  },
  {
    "completion_time": 63034,
    "platform": "WIN",
    "platform_name": "mybrainbad",
    "rank": 64,
    "weapon": 7
  },
  {
    "completion_time": 63046,
    "platform": "WIN",
    "platform_name": "shorts5612",
    "rank": 65,
    "weapon": 7
  },
  {
    "completion_time": 63239,
    "platform": "WIN",
    "platform_name": "nect.",
    "rank": 66,
    "weapon": 7
  },
  {
    "completion_time": 63592,
    "platform": "WIN",
    "platform_name": "MidnightDαwn",
    "rank": 67,
    "weapon": 7
  },
  {
    "completion_time": 64252,
    "platform": "PSN",
    "platform_name": "Boku-bot_",
    "rank": 68,
    "weapon": 7
  },
  {
    "completion_time": 64341,
    "platform": "WIN",
    "platform_name": "Nosnorb94",
    "rank": 69,
    "weapon": 7
  },
  {
    "completion_time": 64651,
    "platform": "PSN",
    "platform_name": "PeepoDevi",
    "rank": 70,
    "weapon": 7
  },
  {
    "completion_time": 65011,
    "platform": "PSN",
    "platform_name": "Tomas108Bmx",
    "rank": 71,
    "weapon": 7
  },
  {
    "completion_time": 65243,
    "platform": "WIN",
    "platform_name": "JesusVR",
    "rank": 72,
    "weapon": 7
  },
  {
    "completion_time": 65252,
    "platform": "WIN",
    "platform_name": "LeafPrime",
    "rank": 73,
    "weapon": 7
  },
  {
    "completion_time": 65343,
    "platform": "WIN",
    "platform_name": "DonEgon",
    "rank": 74,
    "weapon": 7
  },
  {
    "completion_time": 65627,
    "platform": "WIN",
    "platform_name": "JereFlowers_",
    "rank": 75,
    "weapon": 7
  },
  {
    "completion_time": 66208,
    "platform": "WIN",
    "platform_name": "Vее",
    "rank": 76,
    "weapon": 7
  },
  {
    "completion_time": 66371,
    "platform": "PSN",
    "platform_name": "Sensei_Malka",
    "rank": 77,
    "weapon": 7
  },
  {
    "completion_time": 66663,
    "platform": "WIN",
    "platform_name": "thomasflanagan.1",
    "rank": 78,
    "weapon": 7
  },
  {
    "completion_time": 66738,
    "platform": "PSN",
    "platform_name": "Narmo43",
    "rank": 79,
    "weapon": 7
  },
  {
    "completion_time": 66889,
    "platform": "WIN",
    "platform_name": "Mister Pantz",
    "rank": 80,
    "weapon": 7
  },
  {
    "completion_time": 67037,
    "platform": "WIN",
    "platform_name": "Ärå Ärå ÖñêêÇhåñ",
    "rank": 81,
    "weapon": 7
  },
  {
    "completion_time": 67381,
    "platform": "WIN",
    "platform_name": "DyslexicXD",
    "rank": 82,
    "weapon": 7
  },
  {
    "completion_time": 67488,
    "platform": "WIN",
    "platform_name": "Jeiley99",
    "rank": 83,
    "weapon": 7
  },
  {
    "completion_time": 68487,
    "platform": "XBL",
    "platform_name": "Zanubis ッ",
    "rank": 84,
    "weapon": 7
  },
  {
    "completion_time": 68836,
    "platform": "WIN",
    "platform_name": "βeeβo",
    "rank": 85,
    "weapon": 7
  },
  {
    "completion_time": 68866,
    "platform": "WIN",
    "platform_name": "Hvve1",
    "rank": 86,
    "weapon": 7
  },
  {
    "completion_time": 69055,
    "platform": "WIN",
    "platform_name": "楼下老頭",
    "rank": 87,
    "weapon": 7
  },
  {
    "completion_time": 69264,
    "platform": "WIN",
    "platform_name": "SalvajeH",
    "rank": 88,
    "weapon": 7
  },
  {
    "completion_time": 69449,
    "platform": "SWT",
    "platform_name": "Glaser",
    "rank": 89,
    "weapon": 7
  },
  {
    "completion_time": 69653,
    "platform": "WIN",
    "platform_name": "gawzzey",
    "rank": 90,
    "weapon": 7
  },
  {
    "completion_time": 70727,
    "platform": "WIN",
    "platform_name": "uɐS",
    "rank": 91,
    "weapon": 7
  },
  {
    "completion_time": 71007,
    "platform": "PSN",
    "platform_name": "ThedauntlessXD",
    "rank": 92,
    "weapon": 7
  },
  {
    "completion_time": 71170,
    "platform": "WIN",
    "platform_name": "Forseti _-._.-_",
    "rank": 93,
    "weapon": 7
  },
  {
    "completion_time": 71239,
    "platform": "WIN",
    "platform_name": "Vilckas",
    "rank": 94,
    "weapon": 7
  },
  {
    "completion_time": 71474,
    "platform": "PSN",
    "platform_name": "VE__GE__TA",
    "rank": 95,
    "weapon": 7
  },
  {
    "completion_time": 71633,
    "platform": "WIN",
    "platform_name": "NeenskiDaOnly1",
    "rank": 96,
    "weapon": 7
  },
  {
    "completion_time": 71927,
    "platform": "PSN",
    "platform_name": "DarkFaZe-X",
    "rank": 97,
    "weapon": 7
  },
  {
    "completion_time": 71949,
    "platform": "XBL",
    "platform_name": "NiTRO CHRONiC",
    "rank": 98,
    "weapon": 7
  },
  {
    "completion_time": 72076,
    "platform": "PSN",
    "platform_name": "Zepher-07",
    "rank": 99,
    "weapon": 7
  },
  {
    "completion_time": 72515,
    "platform": "WIN",
    "platform_name": "Riz09",
    "rank": 100,
    "weapon": 7
  }
]
